{
  "slug": "aesthetic",
  "tag": "aesthetic",
  "title": "Aesthetic",
  "facet": "vibe",
  "mode": "include",
  "emojis": [
    "☁️",
    "✨️",
    "🌷",
    "🌸",
    "🌻",
    "🍒",
    "🎀",
    "🐚",
    "💫",
    "🕊️",
    "🤍",
    "🥀",
    "🦋",
    "🩰",
    "🪞",
    "🪷",
    "🫧",
    "🫶",
    "🫶🏻",
    "🫶🏼",
    "🫶🏽",
    "🫶🏾",
    "🫶🏿"
  ],
  "count": 23,
  "version": "2026-07-21",
  "emojis_default": [
    "☁️",
    "✨️",
    "🌷",
    "🌸",
    "🌻",
    "🍒",
    "🎀",
    "🐚",
    "💫",
    "🕊️",
    "🤍",
    "🥀",
    "🦋",
    "🩰",
    "🪞",
    "🪷",
    "🫧",
    "🫶"
  ],
  "count_default": 18
}
