{
  "slug": "vehicle",
  "tag": "vehicle",
  "title": "Vehicle",
  "facet": "object",
  "mode": "include",
  "emojis": [
    "⛴️",
    "⛵️",
    "✈️",
    "🏍️",
    "🏎️",
    "🚀",
    "🚁",
    "🚂",
    "🚃",
    "🚄",
    "🚅",
    "🚆",
    "🚇️",
    "🚈",
    "🚊",
    "🚋",
    "🚌",
    "🚍️",
    "🚎",
    "🚐",
    "🚑️",
    "🚒",
    "🚓",
    "🚔️",
    "🚕",
    "🚖",
    "🚗",
    "🚘️",
    "🚙",
    "🚚",
    "🚛",
    "🚜",
    "🚝",
    "🚞",
    "🚟",
    "🚠",
    "🚡",
    "🚢",
    "🚤",
    "🚲️",
    "🛥️",
    "🛩️",
    "🛫",
    "🛬",
    "🛳️",
    "🛴",
    "🛵",
    "🛶",
    "🛸",
    "🛺",
    "🛻"
  ],
  "count": 51,
  "version": "2026-07-21"
}
